{
    "Ar36": {
        "error": 0.0002583330609700523,
        "error_type": "SEM",
        "filter_outliers_dict": {
            "filter_outliers": true,
            "iterations": 1,
            "std_devs": 3,
            "use_iqr_filtering": false,
            "use_standard_deviation_filtering": false
        },
        "fit": "parabolic",
        "fn": 279,
        "include_baseline_error": true,
        "n": 280,
        "outlier_excluded": [
            40
        ],
        "reviewed": true,
        "user_excluded": [],
        "value": 0.00625144955417966
    },
    "Ar37": {
        "error": 0.0040352491146919845,
        "error_type": "SEM",
        "filter_outliers_dict": {
            "filter_outliers": true,
            "iterations": 1,
            "std_devs": 3,
            "use_iqr_filtering": false,
            "use_standard_deviation_filtering": false
        },
        "fit": "linear",
        "fn": 280,
        "include_baseline_error": true,
        "n": 280,
        "outlier_excluded": [],
        "reviewed": true,
        "user_excluded": [],
        "value": -0.02404869494625614
    },
    "Ar38": {
        "error": 0.003192476810566616,
        "error_type": "SEM",
        "filter_outliers_dict": {
            "filter_outliers": true,
            "iterations": 1,
            "std_devs": 3,
            "use_iqr_filtering": false,
            "use_standard_deviation_filtering": false
        },
        "fit": "linear",
        "fn": 277,
        "include_baseline_error": true,
        "n": 280,
        "outlier_excluded": [
            224,
            121,
            61
        ],
        "reviewed": true,
        "user_excluded": [],
        "value": 0.20171983279716227
    },
    "Ar39": {
        "error": 0.0145446876742896,
        "error_type": "SEM",
        "filter_outliers_dict": {
            "filter_outliers": true,
            "iterations": 1,
            "std_devs": 3,
            "use_iqr_filtering": false,
            "use_standard_deviation_filtering": false
        },
        "fit": "parabolic",
        "fn": 278,
        "include_baseline_error": true,
        "n": 280,
        "outlier_excluded": [
            128,
            57
        ],
        "reviewed": true,
        "user_excluded": [],
        "value": 14.15761594547622
    },
    "Ar40": {
        "error": 0.015084673877265004,
        "error_type": "SEM",
        "filter_outliers_dict": {
            "filter_outliers": true,
            "iterations": 1,
            "std_devs": 3,
            "use_iqr_filtering": false,
            "use_standard_deviation_filtering": false
        },
        "fit": "parabolic",
        "fn": 279,
        "include_baseline_error": true,
        "n": 280,
        "outlier_excluded": [
            162
        ],
        "reviewed": true,
        "user_excluded": [],
        "value": 34.70240122342484
    },
    "Ar41": {
        "error": 0.03382387123003131,
        "error_type": "SEM",
        "filter_outliers_dict": {
            "filter_outliers": true,
            "iterations": 1,
            "std_devs": 2
        },
        "fit": "linear",
        "value": -0.42111568146497513
    }
}