{
    "Ar36": {
        "error": 0.00035571410969600746,
        "error_type": "SEM",
        "filter_outliers_dict": {
            "filter_outliers": true,
            "iterations": 1,
            "std_devs": 3,
            "use_iqr_filtering": false,
            "use_standard_deviation_filtering": false
        },
        "fit": "linear",
        "fn": 122,
        "include_baseline_error": true,
        "n": 122,
        "outlier_excluded": [],
        "reviewed": true,
        "user_excluded": [],
        "value": 0.013210084793598783
    },
    "Ar37": {
        "error": 0.005722967487672726,
        "error_type": "SEM",
        "filter_outliers_dict": {
            "filter_outliers": true,
            "iterations": 1,
            "std_devs": 3,
            "use_iqr_filtering": false,
            "use_standard_deviation_filtering": false
        },
        "fit": "linear",
        "fn": 120,
        "include_baseline_error": true,
        "n": 122,
        "outlier_excluded": [
            17,
            111
        ],
        "reviewed": true,
        "user_excluded": [],
        "value": 0.25256793336097866
    },
    "Ar38": {
        "error": 0.0060304641021843705,
        "error_type": "SEM",
        "filter_outliers_dict": {
            "filter_outliers": true,
            "iterations": 1,
            "std_devs": 3,
            "use_iqr_filtering": false,
            "use_standard_deviation_filtering": false
        },
        "fit": "linear",
        "fn": 122,
        "include_baseline_error": true,
        "n": 122,
        "outlier_excluded": [],
        "reviewed": true,
        "user_excluded": [],
        "value": 1.116218181165299
    },
    "Ar39": {
        "error": 0.020008365142834023,
        "error_type": "SEM",
        "filter_outliers_dict": {
            "filter_outliers": true,
            "iterations": 1,
            "std_devs": 3,
            "use_iqr_filtering": false,
            "use_standard_deviation_filtering": false
        },
        "fit": "linear",
        "fn": 122,
        "include_baseline_error": true,
        "n": 122,
        "outlier_excluded": [],
        "reviewed": true,
        "user_excluded": [],
        "value": 89.26076510743795
    },
    "Ar40": {
        "error": 0.03800456641027789,
        "error_type": "SEM",
        "filter_outliers_dict": {
            "filter_outliers": true,
            "iterations": 1,
            "std_devs": 3,
            "use_iqr_filtering": false,
            "use_standard_deviation_filtering": false
        },
        "fit": "linear",
        "fn": 122,
        "include_baseline_error": true,
        "n": 122,
        "outlier_excluded": [],
        "reviewed": true,
        "user_excluded": [],
        "value": 379.3117239434978
    },
    "Ar41": {
        "error": 0.07009760161977369,
        "error_type": "SEM",
        "filter_outliers_dict": {
            "filter_outliers": true,
            "iterations": 1,
            "std_devs": 2
        },
        "fit": "linear",
        "value": -0.08414511441691988
    }
}