{
    "Ar36": {
        "error": 0.00038695475823583323,
        "error_type": "SEM",
        "filter_outliers_dict": {
            "filter_outliers": true,
            "iterations": 1,
            "std_devs": 3,
            "use_iqr_filtering": false,
            "use_standard_deviation_filtering": false
        },
        "fit": "linear",
        "fn": 122,
        "include_baseline_error": true,
        "n": 122,
        "outlier_excluded": [],
        "reviewed": true,
        "user_excluded": [],
        "value": 0.022021503626510824
    },
    "Ar37": {
        "error": 0.0058256325853734805,
        "error_type": "SEM",
        "filter_outliers_dict": {
            "filter_outliers": true,
            "iterations": 1,
            "std_devs": 3,
            "use_iqr_filtering": false,
            "use_standard_deviation_filtering": false
        },
        "fit": "linear",
        "fn": 122,
        "include_baseline_error": true,
        "n": 122,
        "outlier_excluded": [],
        "reviewed": true,
        "user_excluded": [],
        "value": 0.0004935563398603916
    },
    "Ar38": {
        "error": 0.005373387403734267,
        "error_type": "SEM",
        "filter_outliers_dict": {
            "filter_outliers": true,
            "iterations": 1,
            "std_devs": 3,
            "use_iqr_filtering": false,
            "use_standard_deviation_filtering": false
        },
        "fit": "linear",
        "fn": 122,
        "include_baseline_error": true,
        "n": 122,
        "outlier_excluded": [],
        "reviewed": true,
        "user_excluded": [],
        "value": 0.862474348637751
    },
    "Ar39": {
        "error": 0.02060071440138262,
        "error_type": "SEM",
        "filter_outliers_dict": {
            "filter_outliers": true,
            "iterations": 1,
            "std_devs": 3,
            "use_iqr_filtering": false,
            "use_standard_deviation_filtering": false
        },
        "fit": "linear",
        "fn": 121,
        "include_baseline_error": true,
        "n": 122,
        "outlier_excluded": [
            108
        ],
        "reviewed": true,
        "user_excluded": [],
        "value": 68.50298375671042
    },
    "Ar40": {
        "error": 0.024559160744137512,
        "error_type": "SEM",
        "filter_outliers_dict": {
            "filter_outliers": true,
            "iterations": 1,
            "std_devs": 3,
            "use_iqr_filtering": false,
            "use_standard_deviation_filtering": false
        },
        "fit": "linear",
        "fn": 122,
        "include_baseline_error": true,
        "n": 122,
        "outlier_excluded": [],
        "reviewed": true,
        "user_excluded": [],
        "value": 150.40560374066936
    },
    "Ar41": {
        "error": 0.06062077247493617,
        "error_type": "SEM",
        "filter_outliers_dict": {
            "filter_outliers": true,
            "iterations": 1,
            "std_devs": 2
        },
        "fit": "linear",
        "value": -0.2703135078683112
    }
}